stingray/__init__.py
stingray/_astropy_init.py
stingray/_version.py
stingray/base.py
stingray/bexvar.py
stingray/bispectrum.py
stingray/conftest.py
stingray/covariancespectrum.py
stingray/crosscorrelation.py
stingray/crossspectrum.py
stingray/events.py
stingray/exceptions.py
stingray/filters.py
stingray/fourier.py
stingray/gti.py
stingray/io.py
stingray/lightcurve.py
stingray/loggingconfig.py
stingray/lombscargle.py
stingray/multitaper.py
stingray/power_colors.py
stingray/powerspectrum.py
stingray/sampledata.py
stingray/spectroscopy.py
stingray/stats.py
stingray/utils.py
stingray/varenergyspectrum.py
stingray/version.py
stingray/datasets/lc_sample.txt
stingray/datasets/xselect.mdb
stingray/deadtime/__init__.py
stingray/deadtime/fad.py
stingray/deadtime/model.py
stingray/deadtime/tests/__init__.py
stingray/deadtime/tests/test_fad.py
stingray/deadtime/tests/test_models.py
stingray/mission_support/__init__.py
stingray/mission_support/missions.py
stingray/mission_support/rxte.py
stingray/mission_support/tests/__init__.py
stingray/mission_support/tests/test_mission_support.py
stingray/modeling/__init__.py
stingray/modeling/gpmodeling.py
stingray/modeling/parameterestimation.py
stingray/modeling/posterior.py
stingray/modeling/scripts.py
stingray/modeling/tests/__init__.py
stingray/modeling/tests/test_gpmodeling.py
stingray/modeling/tests/test_parameterestimation.py
stingray/modeling/tests/test_posterior.py
stingray/modeling/tests/test_scripts.py
stingray/pulse/__init__.py
stingray/pulse/accelsearch.py
stingray/pulse/fftfit.py
stingray/pulse/modeling.py
stingray/pulse/pulsar.py
stingray/pulse/search.py
stingray/pulse/overlapandsave/README.md
stingray/pulse/overlapandsave/__init__.py
stingray/pulse/overlapandsave/ols.py
stingray/pulse/overlapandsave/test_ols.py
stingray/pulse/tests/__init__.py
stingray/pulse/tests/test_accelsearch.py
stingray/pulse/tests/test_modeling.py
stingray/pulse/tests/test_pulse.py
stingray/pulse/tests/test_search.py
stingray-2.2.10.dist-info/LICENSE.rst
stingray-2.2.10.dist-info/METADATA
stingray-2.2.10.dist-info/WHEEL
stingray-2.2.10.dist-info/top_level.txt
stingray-2.2.10.dist-info/RECORD
