Metadata-Version: 2.1
Name: stingray
Version: 2.2.10
Summary: Time Series Methods For Astronomical X-ray Data
Author-email: Stingray Developers <spectraltiming-stingray@googlegroups.com>
License: MIT
Project-URL: homepage, https://stingray.science
Project-URL: documentation, https://docs.stingray.science
Project-URL: repository, https://github.com/stingraysoftware/stingray
Keywords: astronomy,astrophysics,time series,X-ray,data analysis,black holes,neutron stars,pulsars,space,science
Classifier: Intended Audience :: Science/Research
Classifier: License :: OSI Approved :: MIT License
Classifier: Operating System :: OS Independent
Classifier: Programming Language :: Python :: 3
Classifier: Programming Language :: Python :: Implementation :: CPython
Classifier: Topic :: Scientific/Engineering :: Astronomy
Classifier: Topic :: Scientific/Engineering :: Physics
Requires-Python: >=3.8
License-File: LICENSE.rst
Requires-Dist: numpy >=1.17
Requires-Dist: astropy >=4.0
Requires-Dist: scipy >=1.1.0
Requires-Dist: matplotlib !=3.4.00,>=3.0
Provides-Extra: all
Requires-Dist: stingray[recommended] ; extra == 'all'
Requires-Dist: jplephem ; extra == 'all'
Requires-Dist: emcee >=3.0.0 ; extra == 'all'
Requires-Dist: corner ; extra == 'all'
Requires-Dist: lightkurve ; extra == 'all'
Requires-Dist: pint-pulsar ; extra == 'all'
Requires-Dist: numcodecs ; extra == 'all'
Requires-Dist: xarray ; extra == 'all'
Requires-Dist: pyarrow ; extra == 'all'
Requires-Dist: pandas ; extra == 'all'
Requires-Dist: ultranest ; extra == 'all'
Requires-Dist: jax ; extra == 'all'
Requires-Dist: tinygp ; extra == 'all'
Requires-Dist: jaxns ; extra == 'all'
Requires-Dist: etils ; extra == 'all'
Requires-Dist: tfp-nightly ; extra == 'all'
Requires-Dist: typing-extensions ; extra == 'all'
Requires-Dist: fsspec ; extra == 'all'
Provides-Extra: docs
Requires-Dist: jinja2 ==3.1.3 ; extra == 'docs'
Requires-Dist: docutils ; extra == 'docs'
Requires-Dist: sphinx-astropy ; extra == 'docs'
Requires-Dist: nbsphinx !=0.8.8,>=0.8.3 ; extra == 'docs'
Requires-Dist: nbconvert <7.14 ; extra == 'docs'
Requires-Dist: pandoc ; extra == 'docs'
Requires-Dist: ipython ; extra == 'docs'
Requires-Dist: towncrier <22.12.0 ; extra == 'docs'
Requires-Dist: tomli >=1.1.0 ; (python_version < "3.11") and extra == 'docs'
Provides-Extra: recommended
Requires-Dist: numba ; extra == 'recommended'
Requires-Dist: h5py ; extra == 'recommended'
Requires-Dist: pyyaml ; extra == 'recommended'
Requires-Dist: statsmodels ; extra == 'recommended'
Requires-Dist: pyfftw ; extra == 'recommended'
Provides-Extra: test
Requires-Dist: pytest ; extra == 'test'
Requires-Dist: pytest-astropy ; extra == 'test'
Provides-Extra: test_all
Requires-Dist: astropy[test] ; extra == 'test_all'
Requires-Dist: objgraph ; extra == 'test_all'
Requires-Dist: ipython >=4.2 ; extra == 'test_all'
Requires-Dist: coverage[toml] ; extra == 'test_all'
Requires-Dist: skyfield >=1.20 ; extra == 'test_all'
Requires-Dist: sgp4 >=2.3 ; extra == 'test_all'
